goldencopy.py
GoldenCopy-1.3.4.dist-info/LICENSE.txt
GoldenCopy-1.3.4.dist-info/METADATA
GoldenCopy-1.3.4.dist-info/WHEEL
GoldenCopy-1.3.4.dist-info/entry_points.txt
GoldenCopy-1.3.4.dist-info/top_level.txt
GoldenCopy-1.3.4.dist-info/RECORD
