Metadata-Version: 2.1
Name: GoldenCopy
Version: 1.3.4
Summary: Copy the properties and groups of a user or computer from neo4j (bloodhound) to create an identical golden ticket.
Home-page: https://github.com/Dramelac/GoldenCopy
Author: Dramelac
Author-email: dramelac@pm.me
License: GNU
Project-URL: Bug Reports, https://github.com/Dramelac/GoldenCopy/issues
Project-URL: Source, https://github.com/Dramelac/GoldenCopy
Keywords: pentest redteam goldenticket goldencopy
Classifier: Programming Language :: Python :: 3.6
Classifier: Programming Language :: Python :: 3.7
Classifier: Programming Language :: Python :: 3.8
Classifier: Programming Language :: Python :: 3.9
Classifier: Programming Language :: Python :: 3.10
Classifier: License :: OSI Approved :: GNU General Public License v3 (GPLv3)
Classifier: Operating System :: OS Independent
Requires-Python: >=3.6, <4
License-File: LICENSE.txt
Requires-Dist: py2neo (>=2021.2.3)
